simbricks/orchestration/__init__.py
simbricks/orchestration/helpers/__init__.py
simbricks/orchestration/helpers/exceptions.py
simbricks/orchestration/helpers/instantiation.py
simbricks/orchestration/helpers/simulation.py
simbricks/orchestration/helpers/system.py
simbricks/orchestration/instantiation/__init__.py
simbricks/orchestration/instantiation/base.py
simbricks/orchestration/instantiation/dependency_graph.py
simbricks/orchestration/instantiation/fragment.py
simbricks/orchestration/instantiation/proxy.py
simbricks/orchestration/instantiation/socket.py
simbricks/orchestration/simulation/__init__.py
simbricks/orchestration/simulation/base.py
simbricks/orchestration/simulation/channel.py
simbricks/orchestration/simulation/host.py
simbricks/orchestration/simulation/mem.py
simbricks/orchestration/simulation/net/__init__.py
simbricks/orchestration/simulation/net/net_base.py
simbricks/orchestration/simulation/net/ns3_components.py
simbricks/orchestration/simulation/pcidev.py
simbricks/orchestration/system/__init__.py
simbricks/orchestration/system/base.py
simbricks/orchestration/system/disk_images.py
simbricks/orchestration/system/eth.py
simbricks/orchestration/system/host/__init__.py
simbricks/orchestration/system/host/app.py
simbricks/orchestration/system/host/base.py
simbricks/orchestration/system/mem.py
simbricks/orchestration/system/nic.py
simbricks/orchestration/system/pcie.py
simbricks_orchestration-0.3.6.dist-info/METADATA
simbricks_orchestration-0.3.6.dist-info/WHEEL
simbricks_orchestration-0.3.6.dist-info/RECORD
